{
  "name": "Tachibana Lima",
  "tier": 2,
  "description": "A small and relatively fast destroyer. For her size, Tachibana L boasted a sufficiently powerful torpedo armament. The ship's artillery comprised several rapid-fire small caliber guns.",
  "profile": {
    "health": 7000,
    "artillery": {
      "reload": 5,
      "range": 8,
      "traverseTime": 16.36,
      "shells": {
        "he": {
          "damage": 1300,
          "velocity": 680,
          "mass": 6,
          "fireChance": 6
        },
        "sap": null,
        "ap": {
          "damage": 1000,
          "velocity": 690,
          "mass": 7
        }
      }
    },
    "torpedoes": {
      "range": 5,
      "reload": 22,
      "visibility": 0.7
    },
    "concealment": 5.4,
    "airConcealment": 1.9,
    "speed": 30,
    "rudderTime": 1.9,
    "turnRadius": 450
  },
  "images": {
    "small": "https://glossary-wows-global.gcdn.co/icons//vehicle/small/PJSD014_74630ef07ccf351532f0e1f334212f1b3c08dceb1885c2ea05b865d81a6046a5.png",
    "large": "https://glossary-wows-global.gcdn.co/icons//vehicle/large/PJSD014_0c72cb60056d14c9aa0eb0d1f306dcf89f8711f875636e129dae765c984401e4.png",
    "medium": "https://glossary-wows-global.gcdn.co/icons//vehicle/medium/PJSD014_9db612cee1fc5c358a9cf3a097a8d083cc1357fc0b16e97e1c5fbf95f10f3da2.png",
    "contour": "https://glossary-wows-global.gcdn.co/icons//vehicle/contour/PJSD014_5024eeccd830a8be27cfa314ddf653283f9472f6e0866716a1f6dd0bf13a3aa1.png"
  }
}